QuizEngine4Trivia/__init__.py
QuizEngine4Trivia/models/__init__.py
QuizEngine4Trivia_TirsvadCLI-0.0.6.dist-info/LICENSE
QuizEngine4Trivia_TirsvadCLI-0.0.6.dist-info/METADATA
QuizEngine4Trivia_TirsvadCLI-0.0.6.dist-info/WHEEL
QuizEngine4Trivia_TirsvadCLI-0.0.6.dist-info/top_level.txt
QuizEngine4Trivia_TirsvadCLI-0.0.6.dist-info/RECORD
