Metadata-Version: 2.1
Name: QuizEngine4Trivia-TirsvadCLI
Version: 0.0.6
Summary: Question Engine for Trivia Queston DB
Author: Jens Tirsvad Nielsen
License: GNU GENERAL PUBLIC LICENSE
Project-URL: Homepage, https://github.com/TirsvadCLI
Keywords: trivia,quiz,python
Classifier: License :: OSI Approved :: GNU Affero General Public License v3 or later (AGPLv3+)
Classifier: Programming Language :: Python :: 3
Classifier: Programming Language :: Python :: 3.10
Classifier: Programming Language :: Python :: 3.11
Classifier: Environment :: Console
Classifier: Operating System :: OS Independent
Classifier: Topic :: Software Development :: Libraries :: Python Modules
Requires-Python: >=3.8
License-File: LICENSE
Requires-Dist: requests >=2.32.0
